Workbook

Sheet Raw_Data
A1: Row ID | B1: Order ID | C1: Order Date | D1: Ship Date | E1: Ship Mode | F1: Customer ID | G1: Customer Name | H1: Segment | I1: Country | J1: City | K1: State | L1: Postal Code | M1: Region | N1: Product ID | O1: Category | P1: Sub-Category | Q1: Product Name | R1: Sales | S1: Quantity | T1: Discount | U1: Profit
A2: 519 | B2: CA-2022-10518 | C2: 44562 | D2: 44565 | E2: First Class | F2: CG-2377 | G2: Customer 75 | H2: Consumer | I2: United States | J2: Jacksonville | K2: Jacksonville | L2: 64176 | M2: South | N2: PROD-893 | O2: Furniture | P2: Chairs | Q2: Chairs Product 2 | R2: $149.91 | S2: 1 | T2: 0.05 | U2: $15.30
A3: 350 | B3: CA-2022-10349 | C3: 44562 | D3: 44566 | E3: Standard Class | F3: CG-3064 | G3: Customer 71 | H3: Corporate | I3: United States | J3: Minneapolis | K3: Minneapolis | L3: 43085 | M3: Central | N3: PROD-908 | O3: Office Supplies | P3: Labels | Q3: Labels Product 19 | R3: $47.80 | S3: 2 | T3: 0.3 | U3: $3.80
A4: 149 | B4: CA-2022-10148 | C4: 44562 | D4: 44565 | E4: Second Class | F4: CG-9365 | G4: Customer 87 | H4: Corporate | I4: United States | J4: Chicago | K4: Chicago | L4: 62893 | M4: Central | N4: PROD-530 | O4: Office Supplies | P4: Labels | Q4: Labels Product 23 | R4: $68.62 | S4: 7 | T4: 0.4 | U4: -$4.39
A5: 13 | B5: CA-2022-10012 | C5: 44563 | D5: 44569 | E5: Standard Class | F5: CG-2648 | G5: Customer 104 | H5: Home Office | I5: United States | J5: New York | K5: New York | L5: 71267 | M5: East | N5: PROD-353 | O5: Technology | P5: Phones | Q5: Phones Product 3 | R5: $364.79 | S5: 3 | T5: 0.3 | U5: $37.00
A6: 179 | B6: CA-2022-10178 | C6: 44564 | D6: 44566 | E6: First Class | F6: CG-3743 | G6: Customer 64 | H6: Consumer | I6: United States | J6: San Francisco | K6: San Francisco | L6: 83402 | M6: West | N6: PROD-189 | O6: Office Supplies | P6: Labels | Q6: Labels Product 30 | R6: $38.08 | S6: 3 | T6: 0.1 | U6: $5.17
A7: 48 | B7: CA-2022-10047 | C7: 44566 | D7: 44568 | E7: Second Class | F7: CG-6984 | G7: Customer 23 | H7: Consumer | I7: United States | J7: Philadelphia | K7: Philadelphia | L7: 28574 | M7: East | N7: PROD-764 | O7: Office Supplies | P7: Art | Q7: Art Product 17 | R7: $89.77 | S7: 7 | T7: 0.2 | U7: $8.64
A8: 175 | B8: CA-2022-10174 | C8: 44573 | D8: 44574 | E8: First Class | F8: CG-9835 | G8: Customer 104 | H8: Home Office | I8: United States | J8: Chicago | K8: Chicago | L8: 12204 | M8: Central | N8: PROD-709 | O8: Office Supplies | P8: Labels | Q8: Labels Product 2 | R8: $39.60 | S8: 1 | T8: 0.2 | U8: $0.51
A9: 541 | B9: CA-2022-10540 | C9: 44575 | D9: 44578 | E9: Standard Class | F9: CG-3649 | G9: Customer 52 | H9: Consumer | I9: United States | J9: Nashville | K9: Nashville | L9: 91147 | M9: South | N9: PROD-107 | O9: Technology | P9: Phones | Q9: Phones Product 11 | R9: $284.54 | S9: 7 | T9: 0.3 | U9: $10.88
A10: 88 | B10: CA-2022-10087 | C10: 44582 | D10: 44586 | E10: Standard Class | F10: CG-3365 | G10: Customer 60 | H10: Home Office | I10: United States | J10: Minneapolis | K10: Minneapolis | L10: 80135 | M10: Central | N10: PROD-330 | O10: Technology | P10: Copiers | Q10: Copiers Product 25 | R10: $258.92 | S10: 6 | T10: 0.15 | U10: $9.81
A11: 477 | B11: CA-2022-10476 | C11: 44584 | D11: 44587 | E11: Standard Class | F11: CG-9146 | G11: Customer 21 | H11: Consumer | I11: United States | J11: New York | K11: New York | L11: 67395 | M11: East | N11: PROD-437 | O11: Office Supplies | P11: Art | Q11: Art Product 11 | R11: $16.13 | S11: 4 | T11: 0.15 | U11: $3.33
A12: 163 | B12: CA-2022-10162 | C12: 44586 | D12: 44590 | E12: Second Class | F12: CG-5897 | G12: Customer 128 | H12: Home Office | I12: United States | J12: Chicago | K12: Chicago | L12: 18605 | M12: Central | N12: PROD-457 | O12: Furniture | P12: Furnishings | Q12: Furnishings Product 11 | R12: $217.73 | S12: 4 | T12: 0.2 | U12: -$3.27
A13: 433 | B13: CA-2022-10432 | C13: 44587 | D13: 44591 | E13: Standard Class | F13: CG-1556 | G13: Customer 137 | H13: Consumer | I13: United States | J13: Jacksonville | K13: Jacksonville | L13: 44815 | M13: South | N13: PROD-249 | O13: Office Supplies | P13: Paper | Q13: Paper Product 18 | R13: $93.80 | S13: 6 | T13: 0.15 | U13: $18.11
... A601: 294 | B601: CA-2024-10293 | C601: 45654 | D601: 45657 | E601: First Class | F601: CG-8533 | G601: Customer 9 | H601: Corporate | I601: United States | J601: Charlotte | K601: Charlotte | L601: 69658 | M601: South | N601: PROD-710 | O601: Technology | P601: Machines | Q601: Machines Product 5 | R601: $108.23 | S601: 3 | T601: 0 | U601: $31.96

Sheet Analysis_Data
A1: Row ID | B1: Order ID | C1: Order Date | D1: Ship Date | E1: Ship Mode | F1: Customer ID | G1: Customer Name | H1: Segment | I1: Country | J1: City | K1: State | L1: Postal Code | M1: Region | N1: Product ID | O1: Category | P1: Sub-Category | Q1: Product Name | R1: Sales | S1: Quantity | T1: Discount | U1: Profit | V1: Salesperson | W1: Territory | X1: Profit Margin % | Y1: Order Value | Z1: Year | AA1: Month | AB1: Performance
A2: 519 | B2: CA-2022-10518 | C2: 44562 | D2: 44565 | E2: First Class | F2: CG-2377 | G2: Customer 75 | H2: Consumer | I2: United States | J2: Jacksonville | K2: Jacksonville | L2: 64176 | M2: South | N2: PROD-893 | O2: Furniture | P2: Chairs | Q2: Chairs Product 2 | R2: $149.91 | S2: 1 | T2: 0.05 | U2: $15.30 | V2: =CHOOSE(MOD(SalesData[[#This Row],[Row ID]]-1,8)+1,"Aarav Sharma","Ananya Singh","Rohan Verma","Priya Gupta","Arjun Mehta","Neha Kapoor","Rahul Joshi","Sneha Patel") -> Rahul Joshi | W2: =IF(SalesData[[#This Row],[Salesperson]]="Aarav Sharma","North",IF(SalesData[[#This Row],[Salesperson]]="Ananya Singh","South",IF(SalesData[[#This Row],[Salesperson]]="Rohan Verma","East",IF(SalesData[[#This Row],[Salesperson]]="Priya Gupta","West",IF(SalesData[[#This Row],[Salesperson]]="Arjun Mehta","North",IF(SalesData[[#This Row],[Salesperson]]="Neha Kapoor","South",IF(SalesData[[#This Row],[Salesperson]]="Rahul Joshi","East","West"))))))) -> East | X2: =IFERROR(VALUE(SUBSTITUTE(SUBSTITUTE(SalesData[[#This Row],[Profit]],"$",""),",",""))/VALUE(SUBSTITUTE(SUBSTITUTE(SalesData[[#This Row],[Sales]],"$",""),",","")),0) -> 0.10206124 | Y2: =IFERROR(VALUE(SUBSTITUTE(SUBSTITUTE(SalesData[[#This Row],[Sales]],"$",""),",",""))/SalesData[[#This Row],[Quantity]],0) -> 149.91 | Z2: =YEAR(SalesData[[#This Row],[Order Date]]) -> 2022 | AA2: =TEXT(SalesData[[#This Row],[Order Date]],"mmm") -> Jan | AB2: =IF(AND(SalesData[[#This Row],[Profit Margin %]]>=0.15,SalesData[[#This Row],[Profit]]>0),"High Performer",IF(AND(SalesData[[#This Row],[Profit Margin %]]>=0.05,SalesData[[#This Row],[Profit]]>=0),"Average Performer","Needs Improvement")) -> Average Performer
A3: 350 | B3: CA-2022-10349 | C3: 44562 | D3: 44566 | E3: Standard Class | F3: CG-3064 | G3: Customer 71 | H3: Corporate | I3: United States | J3: Minneapolis | K3: Minneapolis | L3: 43085 | M3: Central | N3: PROD-908 | O3: Office Supplies | P3: Labels | Q3: Labels Product 19 | R3: $47.80 | S3: 2 | T3: 0.3 | U3: $3.80 | V3: =CHOOSE(MOD(SalesData[[#This Row],[Row ID]]-1,8)+1,"Aarav Sharma","Ananya Singh","Rohan Verma","Priya Gupta","Arjun Mehta","Neha Kapoor","Rahul Joshi","Sneha Patel") -> Neha Kapoor | W3: =IF(SalesData[[#This Row],[Salesperson]]="Aarav Sharma","North",IF(SalesData[[#This Row],[Salesperson]]="Ananya Singh","South",IF(SalesData[[#This Row],[Salesperson]]="Rohan Verma","East",IF(SalesData[[#This Row],[Salesperson]]="Priya Gupta","West",IF(SalesData[[#This Row],[Salesperson]]="Arjun Mehta","North",IF(SalesData[[#This Row],[Salesperson]]="Neha Kapoor","South",IF(SalesData[[#This Row],[Salesperson]]="Rahul Joshi","East","West"))))))) -> South | X3: =IFERROR(VALUE(SUBSTITUTE(SUBSTITUTE(SalesData[[#This Row],[Profit]],"$",""),",",""))/VALUE(SUBSTITUTE(SUBSTITUTE(SalesData[[#This Row],[Sales]],"$",""),",","")),0) -> 0.079497908 | Y3: =IFERROR(VALUE(SUBSTITUTE(SUBSTITUTE(SalesData[[#This Row],[Sales]],"$",""),",",""))/SalesData[[#This Row],[Quantity]],0) -> 23.9 | Z3: =YEAR(SalesData[[#This Row],[Order Date]]) -> 2022 | AA3: =TEXT(SalesData[[#This Row],[Order Date]],"mmm") -> Jan | AB3: =IF(AND(SalesData[[#This Row],[Profit Margin %]]>=0.15,SalesData[[#This Row],[Profit]]>0),"High Performer",IF(AND(SalesData[[#This Row],[Profit Margin %]]>=0.05,SalesData[[#This Row],[Profit]]>=0),"Average Performer","Needs Improvement")) -> Average Performer
A4: 149 | B4: CA-2022-10148 | C4: 44562 | D4: 44565 | E4: Second Class | F4: CG-9365 | G4: Customer 87 | H4: Corporate | I4: United States | J4: Chicago | K4: Chicago | L4: 62893 | M4: Central | N4: PROD-530 | O4: Office Supplies | P4: Labels | Q4: Labels Product 23 | R4: $68.62 | S4: 7 | T4: 0.4 | U4: -$4.39 | V4: =CHOOSE(MOD(SalesData[[#This Row],[Row ID]]-1,8)+1,"Aarav Sharma","Ananya Singh","Rohan Verma","Priya Gupta","Arjun Mehta","Neha Kapoor","Rahul Joshi","Sneha Patel") -> Arjun Mehta | W4: =IF(SalesData[[#This Row],[Salesperson]]="Aarav Sharma","North",IF(SalesData[[#This Row],[Salesperson]]="Ananya Singh","South",IF(SalesData[[#This Row],[Salesperson]]="Rohan Verma","East",IF(SalesData[[#This Row],[Salesperson]]="Priya Gupta","West",IF(SalesData[[#This Row],[Salesperson]]="Arjun Mehta","North",IF(SalesData[[#This Row],[Salesperson]]="Neha Kapoor","South",IF(SalesData[[#This Row],[Salesperson]]="Rahul Joshi","East","West"))))))) -> North | X4: =IFERROR(VALUE(SUBSTITUTE(SUBSTITUTE(SalesData[[#This Row],[Profit]],"$",""),",",""))/VALUE(SUBSTITUTE(SUBSTITUTE(SalesData[[#This Row],[Sales]],"$",""),",","")),0) -> -0.063975517 | Y4: =IFERROR(VALUE(SUBSTITUTE(SUBSTITUTE(SalesData[[#This Row],[Sales]],"$",""),",",""))/SalesData[[#This Row],[Quantity]],0) -> 9.8028571 | Z4: =YEAR(SalesData[[#This Row],[Order Date]]) -> 2022 | AA4: =TEXT(SalesData[[#This Row],[Order Date]],"mmm") -> Jan | AB4: =IF(AND(SalesData[[#This Row],[Profit Margin %]]>=0.15,SalesData[[#This Row],[Profit]]>0),"High Performer",IF(AND(SalesData[[#This Row],[Profit Margin %]]>=0.05,SalesData[[#This Row],[Profit]]>=0),"Average Performer","Needs Improvement")) -> Needs Improvement
A5: 13 | B5: CA-2022-10012 | C5: 44563 | D5: 44569 | E5: Standard Class | F5: CG-2648 | G5: Customer 104 | H5: Home Office | I5: United States | J5: New York | K5: New York | L5: 71267 | M5: East | N5: PROD-353 | O5: Technology | P5: Phones | Q5: Phones Product 3 | R5: $364.79 | S5: 3 | T5: 0.3 | U5: $37.00 | V5: =CHOOSE(MOD(SalesData[[#This Row],[Row ID]]-1,8)+1,"Aarav Sharma","Ananya Singh","Rohan Verma","Priya Gupta","Arjun Mehta","Neha Kapoor","Rahul Joshi","Sneha Patel") -> Arjun Mehta | W5: =IF(SalesData[[#This Row],[Salesperson]]="Aarav Sharma","North",IF(SalesData[[#This Row],[Salesperson]]="Ananya Singh","South",IF(SalesData[[#This Row],[Salesperson]]="Rohan Verma","East",IF(SalesData[[#This Row],[Salesperson]]="Priya Gupta","West",IF(SalesData[[#This Row],[Salesperson]]="Arjun Mehta","North",IF(SalesData[[#This Row],[Salesperson]]="Neha Kapoor","South",IF(SalesData[[#This Row],[Salesperson]]="Rahul Joshi","East","West"))))))) -> North | X5: =IFERROR(VALUE(SUBSTITUTE(SUBSTITUTE(SalesData[[#This Row],[Profit]],"$",""),",",""))/VALUE(SUBSTITUTE(SUBSTITUTE(SalesData[[#This Row],[Sales]],"$",""),",","")),0) -> 0.10142822 | Y5: =IFERROR(VALUE(SUBSTITUTE(SUBSTITUTE(SalesData[[#This Row],[Sales]],"$",""),",",""))/SalesData[[#This Row],[Quantity]],0) -> 121.59667 | Z5: =YEAR(SalesData[[#This Row],[Order Date]]) -> 2022 | AA5: =TEXT(SalesData[[#This Row],[Order Date]],"mmm") -> Jan | AB5: =IF(AND(SalesData[[#This Row],[Profit Margin %]]>=0.15,SalesData[[#This Row],[Profit]]>0),"High Performer",IF(AND(SalesData[[#This Row],[Profit Margin %]]>=0.05,SalesData[[#This Row],[Profit]]>=0),"Average Performer","Needs Improvement")) -> Average Performer
A6: 179 | B6: CA-2022-10178 | C6: 44564 | D6: 44566 | E6: First Class | F6: CG-3743 | G6: Customer 64 | H6: Consumer | I6: United States | J6: San Francisco | K6: San Francisco | L6: 83402 | M6: West | N6: PROD-189 | O6: Office Supplies | P6: Labels | Q6: Labels Product 30 | R6: $38.08 | S6: 3 | T6: 0.1 | U6: $5.17 | V6: =CHOOSE(MOD(SalesData[[#This Row],[Row ID]]-1,8)+1,"Aarav Sharma","Ananya Singh","Rohan Verma","Priya Gupta","Arjun Mehta","Neha Kapoor","Rahul Joshi","Sneha Patel") -> Rohan Verma | W6: =IF(SalesData[[#This Row],[Salesperson]]="Aarav Sharma","North",IF(SalesData[[#This Row],[Salesperson]]="Ananya Singh","South",IF(SalesData[[#This Row],[Salesperson]]="Rohan Verma","East",IF(SalesData[[#This Row],[Salesperson]]="Priya Gupta","West",IF(SalesData[[#This Row],[Salesperson]]="Arjun Mehta","North",IF(SalesData[[#This Row],[Salesperson]]="Neha Kapoor","South",IF(SalesData[[#This Row],[Salesperson]]="Rahul Joshi","East","West"))))))) -> East | X6: =IFERROR(VALUE(SUBSTITUTE(SUBSTITUTE(SalesData[[#This Row],[Profit]],"$",""),",",""))/VALUE(SUBSTITUTE(SUBSTITUTE(SalesData[[#This Row],[Sales]],"$",""),",","")),0) -> 0.13576681 | Y6: =IFERROR(VALUE(SUBSTITUTE(SUBSTITUTE(SalesData[[#This Row],[Sales]],"$",""),",",""))/SalesData[[#This Row],[Quantity]],0) -> 12.693333 | Z6: =YEAR(SalesData[[#This Row],[Order Date]]) -> 2022 | AA6: =TEXT(SalesData[[#This Row],[Order Date]],"mmm") -> Jan | AB6: =IF(AND(SalesData[[#This Row],[Profit Margin %]]>=0.15,SalesData[[#This Row],[Profit]]>0),"High Performer",IF(AND(SalesData[[#This Row],[Profit Margin %]]>=0.05,SalesData[[#This Row],[Profit]]>=0),"Average Performer","Needs Improvement")) -> Average Performer
A7: 48 | B7: CA-2022-10047 | C7: 44566 | D7: 44568 | E7: Second Class | F7: CG-6984 | G7: Customer 23 | H7: Consumer | I7: United States | J7: Philadelphia | K7: Philadelphia | L7: 28574 | M7: East | N7: PROD-764 | O7: Office Supplies | P7: Art | Q7: Art Product 17 | R7: $89.77 | S7: 7 | T7: 0.2 | U7: $8.64 | V7: =CHOOSE(MOD(SalesData[[#This Row],[Row ID]]-1,8)+1,"Aarav Sharma","Ananya Singh","Rohan Verma","Priya Gupta","Arjun Mehta","Neha Kapoor","Rahul Joshi","Sneha Patel") -> Sneha Patel | W7: =IF(SalesData[[#This Row],[Salesperson]]="Aarav Sharma","North",IF(SalesData[[#This Row],[Salesperson]]="Ananya Singh","South",IF(SalesData[[#This Row],[Salesperson]]="Rohan Verma","East",IF(SalesData[[#This Row],[Salesperson]]="Priya Gupta","West",IF(SalesData[[#This Row],[Salesperson]]="Arjun Mehta","North",IF(SalesData[[#This Row],[Salesperson]]="Neha Kapoor","South",IF(SalesData[[#This Row],[Salesperson]]="Rahul Joshi","East","West"))))))) -> West | X7: =IFERROR(VALUE(SUBSTITUTE(SUBSTITUTE(SalesData[[#This Row],[Profit]],"$",""),",",""))/VALUE(SUBSTITUTE(SUBSTITUTE(SalesData[[#This Row],[Sales]],"$",""),",","")),0) -> 0.096245962 | Y7: =IFERROR(VALUE(SUBSTITUTE(SUBSTITUTE(SalesData[[#This Row],[Sales]],"$",""),",",""))/SalesData[[#This Row],[Quantity]],0) -> 12.824286 | Z7: =YEAR(SalesData[[#This Row],[Order Date]]) -> 2022 | AA7: =TEXT(SalesData[[#This Row],[Order Date]],"mmm") -> Jan | AB7: =IF(AND(SalesData[[#This Row],[Profit Margin %]]>=0.15,SalesData[[#This Row],[Profit]]>0),"High Performer",IF(AND(SalesData[[#This Row],[Profit Margin %]]>=0.05,SalesData[[#This Row],[Profit]]>=0),"Average Performer","Needs Improvement")) -> Average Performer
A8: 175 | B8: CA-2022-10174 | C8: 44573 | D8: 44574 | E8: First Class | F8: CG-9835 | G8: Customer 104 | H8: Home Office | I8: United States | J8: Chicago | K8: Chicago | L8: 12204 | M8: Central | N8: PROD-709 | O8: Office Supplies | P8: Labels | Q8: Labels Product 2 | R8: $39.60 | S8: 1 | T8: 0.2 | U8: $0.51 | V8: =CHOOSE(MOD(SalesData[[#This Row],[Row ID]]-1,8)+1,"Aarav Sharma","Ananya Singh","Rohan Verma","Priya Gupta","Arjun Mehta","Neha Kapoor","Rahul Joshi","Sneha Patel") -> Rahul Joshi | W8: =IF(SalesData[[#This Row],[Salesperson]]="Aarav Sharma","North",IF(SalesData[[#This Row],[Salesperson]]="Ananya Singh","South",IF(SalesData[[#This Row],[Salesperson]]="Rohan Verma","East",IF(SalesData[[#This Row],[Salesperson]]="Priya Gupta","West",IF(SalesData[[#This Row],[Salesperson]]="Arjun Mehta","North",IF(SalesData[[#This Row],[Salesperson]]="Neha Kapoor","South",IF(SalesData[[#This Row],[Salesperson]]="Rahul Joshi","East","West"))))))) -> East | X8: =IFERROR(VALUE(SUBSTITUTE(SUBSTITUTE(SalesData[[#This Row],[Profit]],"$",""),",",""))/VALUE(SUBSTITUTE(SUBSTITUTE(SalesData[[#This Row],[Sales]],"$",""),",","")),0) -> 0.012878788 | Y8: =IFERROR(VALUE(SUBSTITUTE(SUBSTITUTE(SalesData[[#This Row],[Sales]],"$",""),",",""))/SalesData[[#This Row],[Quantity]],0) -> 39.6 | Z8: =YEAR(SalesData[[#This Row],[Order Date]]) -> 2022 | AA8: =TEXT(SalesData[[#This Row],[Order Date]],"mmm") -> Jan | AB8: =IF(AND(SalesData[[#This Row],[Profit Margin %]]>=0.15,SalesData[[#This Row],[Profit]]>0),"High Performer",IF(AND(SalesData[[#This Row],[Profit Margin %]]>=0.05,SalesData[[#This Row],[Profit]]>=0),"Average Performer","Needs Improvement")) -> Needs Improvement
A9: 541 | B9: CA-2022-10540 | C9: 44575 | D9: 44578 | E9: Standard Class | F9: CG-3649 | G9: Customer 52 | H9: Consumer | I9: United States | J9: Nashville | K9: Nashville | L9: 91147 | M9: South | N9: PROD-107 | O9: Technology | P9: Phones | Q9: Phones Product 11 | R9: $284.54 | S9: 7 | T9: 0.3 | U9: $10.88 | V9: =CHOOSE(MOD(SalesData[[#This Row],[Row ID]]-1,8)+1,"Aarav Sharma","Ananya Singh","Rohan Verma","Priya Gupta","Arjun Mehta","Neha Kapoor","Rahul Joshi","Sneha Patel") -> Arjun Mehta | W9: =IF(SalesData[[#This Row],[Salesperson]]="Aarav Sharma","North",IF(SalesData[[#This Row],[Salesperson]]="Ananya Singh","South",IF(SalesData[[#This Row],[Salesperson]]="Rohan Verma","East",IF(SalesData[[#This Row],[Salesperson]]="Priya Gupta","West",IF(SalesData[[#This Row],[Salesperson]]="Arjun Mehta","North",IF(SalesData[[#This Row],[Salesperson]]="Neha Kapoor","South",IF(SalesData[[#This Row],[Salesperson]]="Rahul Joshi","East","West"))))))) -> North | X9: =IFERROR(VALUE(SUBSTITUTE(SUBSTITUTE(SalesData[[#This Row],[Profit]],"$",""),",",""))/VALUE(SUBSTITUTE(SUBSTITUTE(SalesData[[#This Row],[Sales]],"$",""),",","")),0) -> 0.038237155 | Y9: =IFERROR(VALUE(SUBSTITUTE(SUBSTITUTE(SalesData[[#This Row],[Sales]],"$",""),",",""))/SalesData[[#This Row],[Quantity]],0) -> 40.648571 | Z9: =YEAR(SalesData[[#This Row],[Order Date]]) -> 2022 | AA9: =TEXT(SalesData[[#This Row],[Order Date]],"mmm") -> Jan | AB9: =IF(AND(SalesData[[#This Row],[Profit Margin %]]>=0.15,SalesData[[#This Row],[Profit]]>0),"High Performer",IF(AND(SalesData[[#This Row],[Profit Margin %]]>=0.05,SalesData[[#This Row],[Profit]]>=0),"Average Performer","Needs Improvement")) -> Needs Improvement
A10: 88 | B10: CA-2022-10087 | C10: 44582 | D10: 44586 | E10: Standard Class | F10: CG-3365 | G10: Customer 60 | H10: Home Office | I10: United States | J10: Minneapolis | K10: Minneapolis | L10: 80135 | M10: Central | N10: PROD-330 | O10: Technology | P10: Copiers | Q10: Copiers Product 25 | R10: $258.92 | S10: 6 | T10: 0.15 | U10: $9.81 | V10: =CHOOSE(MOD(SalesData[[#This Row],[Row ID]]-1,8)+1,"Aarav Sharma","Ananya Singh","Rohan Verma","Priya Gupta","Arjun Mehta","Neha Kapoor","Rahul Joshi","Sneha Patel") -> Sneha Patel | W10: =IF(SalesData[[#This Row],[Salesperson]]="Aarav Sharma","North",IF(SalesData[[#This Row],[Salesperson]]="Ananya Singh","South",IF(SalesData[[#This Row],[Salesperson]]="Rohan Verma","East",IF(SalesData[[#This Row],[Salesperson]]="Priya Gupta","West",IF(SalesData[[#This Row],[Salesperson]]="Arjun Mehta","North",IF(SalesData[[#This Row],[Salesperson]]="Neha Kapoor","South",IF(SalesData[[#This Row],[Salesperson]]="Rahul Joshi","East","West"))))))) -> West | X10: =IFERROR(VALUE(SUBSTITUTE(SUBSTITUTE(SalesData[[#This Row],[Profit]],"$",""),",",""))/VALUE(SUBSTITUTE(SUBSTITUTE(SalesData[[#This Row],[Sales]],"$",""),",","")),0) -> 0.037888151 | Y10: =IFERROR(VALUE(SUBSTITUTE(SUBSTITUTE(SalesData[[#This Row],[Sales]],"$",""),",",""))/SalesData[[#This Row],[Quantity]],0) -> 43.153333 | Z10: =YEAR(SalesData[[#This Row],[Order Date]]) -> 2022 | AA10: =TEXT(SalesData[[#This Row],[Order Date]],"mmm") -> Jan | AB10: =IF(AND(SalesData[[#This Row],[Profit Margin %]]>=0.15,SalesData[[#This Row],[Profit]]>0),"High Performer",IF(AND(SalesData[[#This Row],[Profit Margin %]]>=0.05,SalesData[[#This Row],[Profit]]>=0),"Average Performer","Needs Improvement")) -> Needs Improvement
A11: 477 | B11: CA-2022-10476 | C11: 44584 | D11: 44587 | E11: Standard Class | F11: CG-9146 | G11: Customer 21 | H11: Consumer | I11: United States | J11: New York | K11: New York | L11: 67395 | M11: East | N11: PROD-437 | O11: Office Supplies | P11: Art | Q11: Art Product 11 | R11: $16.13 | S11: 4 | T11: 0.15 | U11: $3.33 | V11: =CHOOSE(MOD(SalesData[[#This Row],[Row ID]]-1,8)+1,"Aarav Sharma","Ananya Singh","Rohan Verma","Priya Gupta","Arjun Mehta","Neha Kapoor","Rahul Joshi","Sneha Patel") -> Arjun Mehta | W11: =IF(SalesData[[#This Row],[Salesperson]]="Aarav Sharma","North",IF(SalesData[[#This Row],[Salesperson]]="Ananya Singh","South",IF(SalesData[[#This Row],[Salesperson]]="Rohan Verma","East",IF(SalesData[[#This Row],[Salesperson]]="Priya Gupta","West",IF(SalesData[[#This Row],[Salesperson]]="Arjun Mehta","North",IF(SalesData[[#This Row],[Salesperson]]="Neha Kapoor","South",IF(SalesData[[#This Row],[Salesperson]]="Rahul Joshi","East","West"))))))) -> North | X11: =IFERROR(VALUE(SUBSTITUTE(SUBSTITUTE(SalesData[[#This Row],[Profit]],"$",""),",",""))/VALUE(SUBSTITUTE(SUBSTITUTE(SalesData[[#This Row],[Sales]],"$",""),",","")),0) -> 0.20644761 | Y11: =IFERROR(VALUE(SUBSTITUTE(SUBSTITUTE(SalesData[[#This Row],[Sales]],"$",""),",",""))/SalesData[[#This Row],[Quantity]],0) -> 4.0325 | Z11: =YEAR(SalesData[[#This Row],[Order Date]]) -> 2022 | AA11: =TEXT(SalesData[[#This Row],[Order Date]],"mmm") -> Jan | AB11: =IF(AND(SalesData[[#This Row],[Profit Margin %]]>=0.15,SalesData[[#This Row],[Profit]]>0),"High Performer",IF(AND(SalesData[[#This Row],[Profit Margin %]]>=0.05,SalesData[[#This Row],[Profit]]>=0),"Average Performer","Needs Improvement")) -> High Performer
A12: 163 | B12: CA-2022-10162 | C12: 44586 | D12: 44590 | E12: Second Class | F12: CG-5897 | G12: Customer 128 | H12: Home Office | I12: United States | J12: Chicago | K12: Chicago | L12: 18605 | M12: Central | N12: PROD-457 | O12: Furniture | P12: Furnishings | Q12: Furnishings Product 11 | R12: $217.73 | S12: 4 | T12: 0.2 | U12: -$3.27 | V12: =CHOOSE(MOD(SalesData[[#This Row],[Row ID]]-1,8)+1,"Aarav Sharma","Ananya Singh","Rohan Verma","Priya Gupta","Arjun Mehta","Neha Kapoor","Rahul Joshi","Sneha Patel") -> Rohan Verma | W12: =IF(SalesData[[#This Row],[Salesperson]]="Aarav Sharma","North",IF(SalesData[[#This Row],[Salesperson]]="Ananya Singh","South",IF(SalesData[[#This Row],[Salesperson]]="Rohan Verma","East",IF(SalesData[[#This Row],[Salesperson]]="Priya Gupta","West",IF(SalesData[[#This Row],[Salesperson]]="Arjun Mehta","North",IF(SalesData[[#This Row],[Salesperson]]="Neha Kapoor","South",IF(SalesData[[#This Row],[Salesperson]]="Rahul Joshi","East","West"))))))) -> East | X12: =IFERROR(VALUE(SUBSTITUTE(SUBSTITUTE(SalesData[[#This Row],[Profit]],"$",""),",",""))/VALUE(SUBSTITUTE(SUBSTITUTE(SalesData[[#This Row],[Sales]],"$",""),",","")),0) -> -0.015018601 | Y12: =IFERROR(VALUE(SUBSTITUTE(SUBSTITUTE(SalesData[[#This Row],[Sales]],"$",""),",",""))/SalesData[[#This Row],[Quantity]],0) -> 54.4325 | Z12: =YEAR(SalesData[[#This Row],[Order Date]]) -> 2022 | AA12: =TEXT(SalesData[[#This Row],[Order Date]],"mmm") -> Jan | AB12: =IF(AND(SalesData[[#This Row],[Profit Margin %]]>=0.15,SalesData[[#This Row],[Profit]]>0),"High Performer",IF(AND(SalesData[[#This Row],[Profit Margin %]]>=0.05,SalesData[[#This Row],[Profit]]>=0),"Average Performer","Needs Improvement")) -> Needs Improvement
A13: 433 | B13: CA-2022-10432 | C13: 44587 | D13: 44591 | E13: Standard Class | F13: CG-1556 | G13: Customer 137 | H13: Consumer | I13: United States | J13: Jacksonville | K13: Jacksonville | L13: 44815 | M13: South | N13: PROD-249 | O13: Office Supplies | P13: Paper | Q13: Paper Product 18 | R13: $93.80 | S13: 6 | T13: 0.15 | U13: $18.11 | V13: =CHOOSE(MOD(SalesData[[#This Row],[Row ID]]-1,8)+1,"Aarav Sharma","Ananya Singh","Rohan Verma","Priya Gupta","Arjun Mehta","Neha Kapoor","Rahul Joshi","Sneha Patel") -> Aarav Sharma | W13: =IF(SalesData[[#This Row],[Salesperson]]="Aarav Sharma","North",IF(SalesData[[#This Row],[Salesperson]]="Ananya Singh","South",IF(SalesData[[#This Row],[Salesperson]]="Rohan Verma","East",IF(SalesData[[#This Row],[Salesperson]]="Priya Gupta","West",IF(SalesData[[#This Row],[Salesperson]]="Arjun Mehta","North",IF(SalesData[[#This Row],[Salesperson]]="Neha Kapoor","South",IF(SalesData[[#This Row],[Salesperson]]="Rahul Joshi","East","West"))))))) -> North | X13: =IFERROR(VALUE(SUBSTITUTE(SUBSTITUTE(SalesData[[#This Row],[Profit]],"$",""),",",""))/VALUE(SUBSTITUTE(SUBSTITUTE(SalesData[[#This Row],[Sales]],"$",""),",","")),0) -> 0.19307036 | Y13: =IFERROR(VALUE(SUBSTITUTE(SUBSTITUTE(SalesData[[#This Row],[Sales]],"$",""),",",""))/SalesData[[#This Row],[Quantity]],0) -> 15.633333 | Z13: =YEAR(SalesData[[#This Row],[Order Date]]) -> 2022 | AA13: =TEXT(SalesData[[#This Row],[Order Date]],"mmm") -> Jan | AB13: =IF(AND(SalesData[[#This Row],[Profit Margin %]]>=0.15,SalesData[[#This Row],[Profit]]>0),"High Performer",IF(AND(SalesData[[#This Row],[Profit Margin %]]>=0.05,SalesData[[#This Row],[Profit]]>=0),"Average Performer","Needs Improvement")) -> High Performer
... A601: 294 | B601: CA-2024-10293 | C601: 45654 | D601: 45657 | E601: First Class | F601: CG-8533 | G601: Customer 9 | H601: Corporate | I601: United States | J601: Charlotte | K601: Charlotte | L601: 69658 | M601: South | N601: PROD-710 | O601: Technology | P601: Machines | Q601: Machines Product 5 | R601: $108.23 | S601: 3 | T601: 0 | U601: $31.96 | V601: =CHOOSE(MOD(SalesData[[#This Row],[Row ID]]-1,8)+1,"Aarav Sharma","Ananya Singh","Rohan Verma","Priya Gupta","Arjun Mehta","Neha Kapoor","Rahul Joshi","Sneha Patel") -> Neha Kapoor | W601: =IF(SalesData[[#This Row],[Salesperson]]="Aarav Sharma","North",IF(SalesData[[#This Row],[Salesperson]]="Ananya Singh","South",IF(SalesData[[#This Row],[Salesperson]]="Rohan Verma","East",IF(SalesData[[#This Row],[Salesperson]]="Priya Gupta","West",IF(SalesData[[#This Row],[Salesperson]]="Arjun Mehta","North",IF(SalesData[[#This Row],[Salesperson]]="Neha Kapoor","South",IF(SalesData[[#This Row],[Salesperson]]="Rahul Joshi","East","West"))))))) -> South | X601: =IFERROR(VALUE(SUBSTITUTE(SUBSTITUTE(SalesData[[#This Row],[Profit]],"$",""),",",""))/VALUE(SUBSTITUTE(SUBSTITUTE(SalesData[[#This Row],[Sales]],"$",""),",","")),0) -> 0.29529705 | Y601: =IFERROR(VALUE(SUBSTITUTE(SUBSTITUTE(SalesData[[#This Row],[Sales]],"$",""),",",""))/SalesData[[#This Row],[Quantity]],0) -> 36.076667 | Z601: =YEAR(SalesData[[#This Row],[Order Date]]) -> 2024 | AA601: =TEXT(SalesData[[#This Row],[Order Date]],"mmm") -> Dec | AB601: =IF(AND(SalesData[[#This Row],[Profit Margin %]]>=0.15,SalesData[[#This Row],[Profit]]>0),"High Performer",IF(AND(SalesData[[#This Row],[Profit Margin %]]>=0.05,SalesData[[#This Row],[Profit]]>=0),"Average Performer","Needs Improvement")) -> High Performer

Sheet Salesperson_Summary
A1: Salesperson | B1: Territory | C1: Total Sales | D1: Total Profit | E1: Profit Margin % | F1: Total Quantity | G1: Avg Order Value | H1: Performance | I1: Sales Rank | J1: Profit Rank | K1: Sales 2022 | L1: Sales 2023 | M1: Growth %
A2: Aarav Sharma | B2: North | C2: {=SUMPRODUCT((SalesData[Salesperson]=A2)*SalesData[Order Value]*SalesData[Quantity])} -> 13037.39 | D2: {=SUMPRODUCT((SalesData[Salesperson]=A2)*IFERROR(VALUE(SUBSTITUTE(SUBSTITUTE(SalesData[Profit],"$",""),",","")),0))} -> 1219.12 | E2: =IFERROR(D2/C2,0) -> 0.093509514 | F2: =SUMIF(SalesData[Salesperson],A2,SalesData[Quantity]) -> 298 | G2: =IFERROR(C2/F2,0) -> 43.749631 | H2: =IF(AND(E2>=15%,D2>0),"High Performer",IF(AND(E2>=5%,D2>=0),"Average Performer","Needs Improvement")) -> Average Performer | I2: =_xlfn.RANK.EQ(C2,$C$2:$C$9,0) -> 1 | J2: =_xlfn.RANK.EQ(D2,$D$2:$D$9,0) -> 3 | K2: {=SUMPRODUCT((SalesData[Salesperson]=A2)*(SalesData[Year]=2022)*SalesData[Order Value]*SalesData[Quantity])} -> 3647.22 | L2: {=SUMPRODUCT((SalesData[Salesperson]=A2)*(SalesData[Year]=2023)*SalesData[Order Value]*SalesData[Quantity])} -> 4689.96 | M2: =IFERROR((L2-K2)/K2,0) -> 0.28589995
A3: Ananya Singh | B3: South | C3: {=SUMPRODUCT((SalesData[Salesperson]=A3)*SalesData[Order Value]*SalesData[Quantity])} -> 12664.66 | D3: {=SUMPRODUCT((SalesData[Salesperson]=A3)*IFERROR(VALUE(SUBSTITUTE(SUBSTITUTE(SalesData[Profit],"$",""),",","")),0))} -> 1147.94 | E3: =IFERROR(D3/C3,0) -> 0.090641202 | F3: =SUMIF(SalesData[Salesperson],A3,SalesData[Quantity]) -> 331 | G3: =IFERROR(C3/F3,0) -> 38.261813 | H3: =IF(AND(E3>=15%,D3>0),"High Performer",IF(AND(E3>=5%,D3>=0),"Average Performer","Needs Improvement")) -> Average Performer | I3: =_xlfn.RANK.EQ(C3,$C$2:$C$9,0) -> 4 | J3: =_xlfn.RANK.EQ(D3,$D$2:$D$9,0) -> 4 | K3: {=SUMPRODUCT((SalesData[Salesperson]=A3)*(SalesData[Year]=2022)*SalesData[Order Value]*SalesData[Quantity])} -> 4675.2 | L3: {=SUMPRODUCT((SalesData[Salesperson]=A3)*(SalesData[Year]=2023)*SalesData[Order Value]*SalesData[Quantity])} -> 4719.15 | M3: =IFERROR((L3-K3)/K3,0) -> 0.0094006674
A4: Rohan Verma | B4: East | C4: {=SUMPRODUCT((SalesData[Salesperson]=A4)*SalesData[Order Value]*SalesData[Quantity])} -> 12678.96 | D4: {=SUMPRODUCT((SalesData[Salesperson]=A4)*IFERROR(VALUE(SUBSTITUTE(SUBSTITUTE(SalesData[Profit],"$",""),",","")),0))} -> 996.67 | E4: =IFERROR(D4/C4,0) -> 0.078608182 | F4: =SUMIF(SalesData[Salesperson],A4,SalesData[Quantity]) -> 288 | G4: =IFERROR(C4/F4,0) -> 44.024167 | H4: =IF(AND(E4>=15%,D4>0),"High Performer",IF(AND(E4>=5%,D4>=0),"Average Performer","Needs Improvement")) -> Average Performer | I4: =_xlfn.RANK.EQ(C4,$C$2:$C$9,0) -> 3 | J4: =_xlfn.RANK.EQ(D4,$D$2:$D$9,0) -> 6 | K4: {=SUMPRODUCT((SalesData[Salesperson]=A4)*(SalesData[Year]=2022)*SalesData[Order Value]*SalesData[Quantity])} -> 5379.78 | L4: {=SUMPRODUCT((SalesData[Salesperson]=A4)*(SalesData[Year]=2023)*SalesData[Order Value]*SalesData[Quantity])} -> 3377.4 | M4: =IFERROR((L4-K4)/K4,0) -> -0.37220481
A5: Priya Gupta | B5: West | C5: {=SUMPRODUCT((SalesData[Salesperson]=A5)*SalesData[Order Value]*SalesData[Quantity])} -> 12864.34 | D5: {=SUMPRODUCT((SalesData[Salesperson]=A5)*IFERROR(VALUE(SUBSTITUTE(SUBSTITUTE(SalesData[Profit],"$",""),",","")),0))} -> 1436.25 | E5: =IFERROR(D5/C5,0) -> 0.11164584 | F5: =SUMIF(SalesData[Salesperson],A5,SalesData[Quantity]) -> 278 | G5: =IFERROR(C5/F5,0) -> 46.274604 | H5: =IF(AND(E5>=15%,D5>0),"High Performer",IF(AND(E5>=5%,D5>=0),"Average Performer","Needs Improvement")) -> Average Performer | I5: =_xlfn.RANK.EQ(C5,$C$2:$C$9,0) -> 2 | J5: =_xlfn.RANK.EQ(D5,$D$2:$D$9,0) -> 1 | K5: {=SUMPRODUCT((SalesData[Salesperson]=A5)*(SalesData[Year]=2022)*SalesData[Order Value]*SalesData[Quantity])} -> 3124.22 | L5: {=SUMPRODUCT((SalesData[Salesperson]=A5)*(SalesData[Year]=2023)*SalesData[Order Value]*SalesData[Quantity])} -> 4290.7 | M5: =IFERROR((L5-K5)/K5,0) -> 0.37336679
A6: Arjun Mehta | B6: North | C6: {=SUMPRODUCT((SalesData[Salesperson]=A6)*SalesData[Order Value]*SalesData[Quantity])} -> 10782.71 | D6: {=SUMPRODUCT((SalesData[Salesperson]=A6)*IFERROR(VALUE(SUBSTITUTE(SUBSTITUTE(SalesData[Profit],"$",""),",","")),0))} -> 999.63 | E6: =IFERROR(D6/C6,0) -> 0.09270675 | F6: =SUMIF(SalesData[Salesperson],A6,SalesData[Quantity]) -> 307 | G6: =IFERROR(C6/F6,0) -> 35.122834 | H6: =IF(AND(E6>=15%,D6>0),"High Performer",IF(AND(E6>=5%,D6>=0),"Average Performer","Needs Improvement")) -> Average Performer | I6: =_xlfn.RANK.EQ(C6,$C$2:$C$9,0) -> 7 | J6: =_xlfn.RANK.EQ(D6,$D$2:$D$9,0) -> 5 | K6: {=SUMPRODUCT((SalesData[Salesperson]=A6)*(SalesData[Year]=2022)*SalesData[Order Value]*SalesData[Quantity])} -> 5726.06 | L6: {=SUMPRODUCT((SalesData[Salesperson]=A6)*(SalesData[Year]=2023)*SalesData[Order Value]*SalesData[Quantity])} -> 2050.84 | M6: =IFERROR((L6-K6)/K6,0) -> -0.64184099
A7: Neha Kapoor | B7: South | C7: {=SUMPRODUCT((SalesData[Salesperson]=A7)*SalesData[Order Value]*SalesData[Quantity])} -> 11133.21 | D7: {=SUMPRODUCT((SalesData[Salesperson]=A7)*IFERROR(VALUE(SUBSTITUTE(SUBSTITUTE(SalesData[Profit],"$",""),",","")),0))} -> 1296.54 | E7: =IFERROR(D7/C7,0) -> 0.11645698 | F7: =SUMIF(SalesData[Salesperson],A7,SalesData[Quantity]) -> 270 | G7: =IFERROR(C7/F7,0) -> 41.234111 | H7: =IF(AND(E7>=15%,D7>0),"High Performer",IF(AND(E7>=5%,D7>=0),"Average Performer","Needs Improvement")) -> Average Performer | I7: =_xlfn.RANK.EQ(C7,$C$2:$C$9,0) -> 6 | J7: =_xlfn.RANK.EQ(D7,$D$2:$D$9,0) -> 2 | K7: {=SUMPRODUCT((SalesData[Salesperson]=A7)*(SalesData[Year]=2022)*SalesData[Order Value]*SalesData[Quantity])} -> 2382.01 | L7: {=SUMPRODUCT((SalesData[Salesperson]=A7)*(SalesData[Year]=2023)*SalesData[Order Value]*SalesData[Quantity])} -> 4414.63 | M7: =IFERROR((L7-K7)/K7,0) -> 0.85332135
A8: Rahul Joshi | B8: East | C8: {=SUMPRODUCT((SalesData[Salesperson]=A8)*SalesData[Order Value]*SalesData[Quantity])} -> 10643.54 | D8: {=SUMPRODUCT((SalesData[Salesperson]=A8)*IFERROR(VALUE(SUBSTITUTE(SUBSTITUTE(SalesData[Profit],"$",""),",","")),0))} -> 670.23 | E8: =IFERROR(D8/C8,0) -> 0.062970591 | F8: =SUMIF(SalesData[Salesperson],A8,SalesData[Quantity]) -> 308 | G8: =IFERROR(C8/F8,0) -> 34.556948 | H8: =IF(AND(E8>=15%,D8>0),"High Performer",IF(AND(E8>=5%,D8>=0),"Average Performer","Needs Improvement")) -> Average Performer | I8: =_xlfn.RANK.EQ(C8,$C$2:$C$9,0) -> 8 | J8: =_xlfn.RANK.EQ(D8,$D$2:$D$9,0) -> 8 | K8: {=SUMPRODUCT((SalesData[Salesperson]=A8)*(SalesData[Year]=2022)*SalesData[Order Value]*SalesData[Quantity])} -> 3132.32 | L8: {=SUMPRODUCT((SalesData[Salesperson]=A8)*(SalesData[Year]=2023)*SalesData[Order Value]*SalesData[Quantity])} -> 3132.29 | M8: =IFERROR((L8-K8)/K8,0) -> -9.5775655e-06
A9: Sneha Patel | B9: West | C9: {=SUMPRODUCT((SalesData[Salesperson]=A9)*SalesData[Order Value]*SalesData[Quantity])} -> 11368.28 | D9: {=SUMPRODUCT((SalesData[Salesperson]=A9)*IFERROR(VALUE(SUBSTITUTE(SUBSTITUTE(SalesData[Profit],"$",""),",","")),0))} -> 802.89 | E9: =IFERROR(D9/C9,0) -> 0.07062546 | F9: =SUMIF(SalesData[Salesperson],A9,SalesData[Quantity]) -> 281 | G9: =IFERROR(C9/F9,0) -> 40.456512 | H9: =IF(AND(E9>=15%,D9>0),"High Performer",IF(AND(E9>=5%,D9>=0),"Average Performer","Needs Improvement")) -> Average Performer | I9: =_xlfn.RANK.EQ(C9,$C$2:$C$9,0) -> 5 | J9: =_xlfn.RANK.EQ(D9,$D$2:$D$9,0) -> 7 | K9: {=SUMPRODUCT((SalesData[Salesperson]=A9)*(SalesData[Year]=2022)*SalesData[Order Value]*SalesData[Quantity])} -> 2962.41 | L9: {=SUMPRODUCT((SalesData[Salesperson]=A9)*(SalesData[Year]=2023)*SalesData[Order Value]*SalesData[Quantity])} -> 4672.31 | M9: =IFERROR((L9-K9)/K9,0) -> 0.57719897

Sheet Dashboard
A1: SALESPERSON PERFORMANCE ANALYSIS
A3: TOTAL SALES | F3: TOTAL PROFIT | K3: PROFIT MARGIN | P3: TOTAL QUANTITY
A4: =SUM(Salesperson_Summary!C2:C9) -> 95173.09 | F4: =SUM(Salesperson_Summary!D2:D9) -> 8569.27 | K4: =IFERROR(SUM(Salesperson_Summary!D2:D9)/SUM(Salesperson_Summary!C2:C9),0) -> 0.090038791 | P4: =SUM(Salesperson_Summary!F2:F9) -> 2361
A6: AVERAGE ORDER VALUE | F6: TOP SALESPERSON | K6: TOP PROFIT PERFORMER | P6: AVERAGE GROWTH
A7: =IFERROR(SUM(Salesperson_Summary!C2:C9)/SUM(Salesperson_Summary!F2:F9),0) -> 40.3105 | F7: =INDEX(Salesperson_Summary!A2:A9,MATCH(MAX(Salesperson_Summary!C2:C9),Salesperson_Summary!C2:C9,0)) -> Aarav Sharma | K7: =INDEX(Salesperson_Summary!A2:A9,MATCH(MAX(Salesperson_Summary!D2:D9),Salesperson_Summary!D2:D9,0)) -> Priya Gupta | P7: =AVERAGE(Salesperson_Summary!M2:M9) -> 0.13564154

Sheet Territory_Summary
A1: Territory | B1: Total Sales
A2: North | B2: =SUMIF(Salesperson_Summary!B$2:B$9,A2,Salesperson_Summary!C$2:C$9) -> 23820.1
A3: South | B3: =SUMIF(Salesperson_Summary!B$2:B$9,A3,Salesperson_Summary!C$2:C$9) -> 23797.87
A4: East | B4: =SUMIF(Salesperson_Summary!B$2:B$9,A4,Salesperson_Summary!C$2:C$9) -> 23322.5
A5: West | B5: =SUMIF(Salesperson_Summary!B$2:B$9,A5,Salesperson_Summary!C$2:C$9) -> 24232.62
